keypass/__init__.py
keypass/_version.py
keypass/core.py
keypass-0.1.4.dist-info/METADATA
keypass-0.1.4.dist-info/WHEEL
keypass-0.1.4.dist-info/licenses/LICENSE
keypass-0.1.4.dist-info/RECORD
