Metadata-Version: 2.4
Name: keypass
Version: 0.1.4
Summary: A Python library for secure encryption, decryption, and storage of sensitive data.
Author-email: "kris.wang" <wenhom.wang@gmail.com>
License-Expression: MIT
License-File: LICENSE
Requires-Python: >=3.10
Requires-Dist: cryptography>=44.0.0
Provides-Extra: dev
Requires-Dist: rtoml>=0.12.0; extra == 'dev'
